{
    "year": {
        "start": 0, 
        "length": 4, 
        "stop": 4, 
        "parse_position": 0
    }, 
    "rid": {
        "start": 4, 
        "length": 10, 
        "stop": 14, 
        "parse_position": 1
    }, 
    "agency": {
        "start": 14, 
        "length": 1, 
        "stop": 15, 
        "parse_position": 2
    }, 
    "loan_type": {
        "start": 15, 
        "length": 1, 
        "stop": 16, 
        "parse_position": 3
    }, 
    "loan_purpose": {
        "start": 16, 
        "length": 1, 
        "stop": 17, 
        "parse_position": 4
    }, 
    "occupancy": {
        "start": 17, 
        "length": 1, 
        "stop": 18, 
        "parse_position": 5
    }, 
    "amount": {
        "start": 18, 
        "length": 5, 
        "stop": 23, 
        "parse_position": 6
    }, 
    "action": {
        "start": 23, 
        "length": 1, 
        "stop": 24, 
        "parse_position": 7
    }, 
    "msa": {
        "start": 24, 
        "length": 5, 
        "stop": 29, 
        "parse_position": 8
    }, 
    "state": {
        "start": 29, 
        "length": 2, 
        "stop": 31, 
        "parse_position": 9
    }, 
    "county": {
        "start": 31, 
        "length": 3, 
        "stop": 34, 
        "parse_position": 10
    }, 
    "tract": {
        "start": 34, 
        "length": 7, 
        "stop": 41, 
        "parse_position": 11
    }, 
    "race": {
        "start": 40, 
        "length": 1, 
        "stop": 41, 
        "parse_position": 12
    }, 
    "co_race": {
        "start": 41, 
        "length": 1, 
        "stop": 42, 
        "parse_position": 13
    }, 
    "sex": {
        "start": 41, 
        "length": 1, 
        "stop": 42, 
        "parse_position": 12
    }, 
    "co_sex": {
        "start": 42, 
        "length": 1, 
        "stop": 43, 
        "parse_position": 13
    }, 
    "income": {
        "start": 43, 
        "length": 4, 
        "stop": 47, 
        "parse_position": 14
    }, 
    "purchaser": {
        "start": 47, 
        "length": 1, 
        "stop": 48, 
        "parse_position": 15
    }, 
    "denial1": {
        "start": 48, 
        "length": 1, 
        "stop": 49, 
        "parse_position": 16
    }, 
    "denial2": {
        "start": 49, 
        "length": 1, 
        "stop": 50, 
        "parse_position": 17
    }, 
    "denial3": {
        "start": 50, 
        "length": 1, 
        "stop": 51, 
        "parse_position": 18
    }, 
    "edit_status": {
        "start": 51, 
        "length": 1, 
        "stop": 52, 
        "parse_position": 19
    }, 
    "sequence": {
        "start": 73, 
        "length": 7, 
        "stop": 80, 
        "parse_position": 37
    }, 
    "property_type": {
        "start": 52, 
        "length": 1, 
        "stop": 53, 
        "parse_position": 20
    }, 
    "preapproval": {
        "start": 53, 
        "length": 1, 
        "stop": 54, 
        "parse_position": 21
    }, 
    "ethnicity": {
        "start": 54, 
        "length": 1, 
        "stop": 55, 
        "parse_position": 22
    }, 
    "co_ethnicity": {
        "start": 55, 
        "length": 1, 
        "stop": 56, 
        "parse_position": 23
    }, 
    "race1": {
        "start": 56, 
        "length": 1, 
        "stop": 57, 
        "parse_position": 24
    }, 
    "race2": {
        "start": 57, 
        "length": 1, 
        "stop": 58, 
        "parse_position": 25
    }, 
    "race3": {
        "start": 58, 
        "length": 1, 
        "stop": 59, 
        "parse_position": 26
    }, 
    "race4": {
        "start": 59, 
        "length": 1, 
        "stop": 60, 
        "parse_position": 27
    }, 
    "race5": {
        "start": 60, 
        "length": 1, 
        "stop": 61, 
        "parse_position": 28
    }, 
    "co_race1": {
        "start": 61, 
        "length": 1, 
        "stop": 62, 
        "parse_position": 29
    }, 
    "co_race2": {
        "start": 62, 
        "length": 1, 
        "stop": 63, 
        "parse_position": 30
    }, 
    "co_race3": {
        "start": 63, 
        "length": 1, 
        "stop": 64, 
        "parse_position": 31
    }, 
    "co_race4": {
        "start": 64, 
        "length": 1, 
        "stop": 65, 
        "parse_position": 32
    }, 
    "co_race5": {
        "start": 65, 
        "length": 1, 
        "stop": 66, 
        "parse_position": 33
    }, 
    "rate_spread": {
        "start": 66, 
        "length": 5, 
        "stop": 71, 
        "parse_position": 34
    }, 
    "hoepa": {
        "start": 71, 
        "length": 1, 
        "stop": 72, 
        "parse_position": 35
    }, 
    "lien": {
        "start": 72, 
        "length": 1, 
        "stop": 73, 
        "parse_position": 36
    }
}